diffenv/__init__.py
diffenv/diffviewer.py
diffenv/editor.py
diffenv/main.py
diffenv-0.2.2.data/scripts/diffenv
diffenv-0.2.2.data/scripts/diffenv-nopaging
diffenv-0.2.2.dist-info/LICENSE
diffenv-0.2.2.dist-info/METADATA
diffenv-0.2.2.dist-info/WHEEL
diffenv-0.2.2.dist-info/top_level.txt
diffenv-0.2.2.dist-info/RECORD
