Metadata-Version: 2.1
Name: diffenv
Version: 0.2.2
Summary: Compare development environments
Home-page: http://github.com/error-central/diffenv
Author: Stan James, Gabriel Pickard
Author-email: wanderingstan@gmail.com, wergomat@gmail.com
License: MIT
Platform: UNKNOWN
Requires-Dist: colorama
Requires-Dist: requests
Requires-Dist: ruamel.yaml
Requires-Dist: gitpython
Requires-Dist: psutil
Requires-Dist: importlib-metadata
